kalkon/__init__.py
kalkon/__main__.py
kalkon/gui.py
kalkon/kalkon.py
kalkon/main.py
kalkon/images/kalkon.png
kalkon-0.6.0.dist-info/licenses/LICENSE
kalkon-0.6.0.dist-info/METADATA
kalkon-0.6.0.dist-info/WHEEL
kalkon-0.6.0.dist-info/entry_points.txt
kalkon-0.6.0.dist-info/top_level.txt
kalkon-0.6.0.dist-info/RECORD
