Metadata-Version: 2.4
Name: kalkon
Version: 0.6.0
Summary: Calculator with GUI
Author-email: Fredrik Andersson <freand@gmail.com>
Maintainer-email: Fredrik Andersson <freand@gmail.com>
Project-URL: homepage, https://github.com/freand76/kalkon
Keywords: calculator
Classifier: Programming Language :: Python :: 3
Classifier: Programming Language :: Python :: 3.9
Classifier: Programming Language :: Python :: 3.10
Classifier: Programming Language :: Python :: 3.11
Classifier: Programming Language :: Python :: 3.12
Classifier: Programming Language :: Python :: 3 :: Only
Requires-Python: >=3.9
License-File: LICENSE
Requires-Dist: pyside6>=6.9.0
Requires-Dist: pexpect==4.9.0
Requires-Dist: asteval==1.0.6
Dynamic: license-file
